plotgsheet/__init__.py
plotgsheet-0.0.1.dist-info/METADATA
plotgsheet-0.0.1.dist-info/WHEEL
plotgsheet-0.0.1.dist-info/license.txt
plotgsheet-0.0.1.dist-info/top_level.txt
plotgsheet-0.0.1.dist-info/RECORD
