Metadata-Version: 2.1
Name: plotgsheet
Version: 0.0.1
Summary: This Package is used to Plot diff-diff Graph from Google Sheet.
Home-page: UNKNOWN
Author: Ashok Kumar Meghvanshi
Author-email: ashokmeghvanshi04@gmail.com
License: UNKNOWN
Platform: UNKNOWN
Requires-Dist: pandas (>=1.1.0)
Requires-Dist: gspread (>=3.5.0)
Requires-Dist: matplotlib (>=3.3.0)
